{
  "signing": {
    "default": {
      "expiry": "8760h"
    },
    "profiles": {
      "ca": {
        "expiry": "42720h",
        "usages": [
          "digital signature",
          "cert sign",
          "crl sign",
          "signing",
          "key encipherment"
        ],
        "is_ca": true
      },
      "server": {
        "expiry": "8760h",
        "usages": [
          "key encipherment",
          "server auth"
        ]
      },
      "client": {
        "expiry": "8760h",
        "usages": [
          "key encipherment",
          "client auth"
        ]
      }
    }
  }
}
